imblog/Client.py
imblog/__init__.py
imblog/common/Requests.py
imblog/common/__init__.py
imblog/common/config.py
imblog/common/utils.py
imblog/selenium/__init__.py
imblog/selenium/elements.py
imblog/selenium/locators.py
imblog/selenium/page.py
imblog-0.2.dist-info/METADATA
imblog-0.2.dist-info/WHEEL
imblog-0.2.dist-info/top_level.txt
imblog-0.2.dist-info/RECORD
