Metadata-Version: 2.1
Name: imblog
Version: 0.2
Summary: A Des of imblog
Home-page: https://github.com/vtandroid/imblog
Author: hoa
Author-email: getmoneykhmt3@gmail.com
License: UNKNOWN
Platform: UNKNOWN
Classifier: Programming Language :: Python :: 3
Classifier: License :: OSI Approved :: MIT License
Classifier: Operating System :: OS Independent
Requires-Dist: selenium
Requires-Dist: requests
